{
  "project_info": {
    "project_number": "660747882001",
    "firebase_url": "https://hikewme-6fb06.firebaseio.com",
    "project_id": "hikewme-6fb06",
    "storage_bucket": "hikewme-6fb06.appspot.com"
  },
  "client": [
    {
      "client_info": {
        "mobilesdk_app_id": "1:660747882001:android:8d03182a8af3456b",
        "android_client_info": {
          "package_name": "com.example.judejoseph.bootcamplocator"
        }
      },
      "oauth_client": [
        {
          "client_id": "660747882001-1pejei1otmc60be6uiinqktk0ma3lh3s.apps.googleusercontent.com",
          "client_type": 3
        }
      ],
      "api_key": [
        {
          "current_key": "AIzaSyCii2NnQv2gSH3vaxgzTf3_dXW-gtc0TRI"
        }
      ],
      "services": {
        "analytics_service": {
          "status": 1
        },
        "appinvite_service": {
          "status": 1,
          "other_platform_oauth_client": []
        },
        "ads_service": {
          "status": 2
        }
      }
    }
  ],
  "configuration_version": "1"
}